astro_drpy-0.1.11.dist-info/licenses/LICENSE
drpy/__init__.py
drpy/core.py
drpy/decorate.py
drpy/plotting.py
drpy/utils.py
drpy/validate.py
drpy/batch/__init__.py
drpy/batch/core.py
drpy/image/__init__.py
drpy/image/core.py
drpy/image/utils.py
drpy/modeling/__init__.py
drpy/modeling/core.py
drpy/modeling/function.py
drpy/onedspec/__init__.py
drpy/onedspec/center.py
drpy/onedspec/core.py
drpy/onedspec/io.py
drpy/onedspec/lib/extinction/LJextinct.dat
drpy/onedspec/lib/extinction/baoextinct.dat
drpy/onedspec/lib/onedstds/README
drpy/onedspec/lib/onedstds/ctioextinct.dat
drpy/onedspec/lib/onedstds/kpnoextinct.dat
drpy/onedspec/lib/onedstds/names.men
drpy/onedspec/lib/onedstds/blackbody/b.dat
drpy/onedspec/lib/onedstds/blackbody/h.dat
drpy/onedspec/lib/onedstds/blackbody/i.dat
drpy/onedspec/lib/onedstds/blackbody/j.dat
drpy/onedspec/lib/onedstds/blackbody/k.dat
drpy/onedspec/lib/onedstds/blackbody/l.dat
drpy/onedspec/lib/onedstds/blackbody/lprime.dat
drpy/onedspec/lib/onedstds/blackbody/m.dat
drpy/onedspec/lib/onedstds/blackbody/mkbbcal.cl
drpy/onedspec/lib/onedstds/blackbody/mkbbdat.cl
drpy/onedspec/lib/onedstds/blackbody/params.dat
drpy/onedspec/lib/onedstds/blackbody/r.dat
drpy/onedspec/lib/onedstds/blackbody/standards.men
drpy/onedspec/lib/onedstds/blackbody/u.dat
drpy/onedspec/lib/onedstds/blackbody/v.dat
drpy/onedspec/lib/onedstds/bstdscal/hr3454.dat
drpy/onedspec/lib/onedstds/bstdscal/hr3982.dat
drpy/onedspec/lib/onedstds/bstdscal/hr4468.dat
drpy/onedspec/lib/onedstds/bstdscal/hr4534.dat
drpy/onedspec/lib/onedstds/bstdscal/hr5191.dat
drpy/onedspec/lib/onedstds/bstdscal/hr5511.dat
drpy/onedspec/lib/onedstds/bstdscal/hr7001.dat
drpy/onedspec/lib/onedstds/bstdscal/hr718.dat
drpy/onedspec/lib/onedstds/bstdscal/hr7596.dat
drpy/onedspec/lib/onedstds/bstdscal/hr7950.dat
drpy/onedspec/lib/onedstds/bstdscal/hr8634.dat
drpy/onedspec/lib/onedstds/bstdscal/hr9087.dat
drpy/onedspec/lib/onedstds/bstdscal/names.men
drpy/onedspec/lib/onedstds/bstdscal/standards.men
drpy/onedspec/lib/onedstds/calspec/hd159222_stis_008.fits
astro_drpy-0.1.11.dist-info/METADATA
astro_drpy-0.1.11.dist-info/WHEEL
astro_drpy-0.1.11.dist-info/top_level.txt
astro_drpy-0.1.11.dist-info/RECORD
