Metadata-Version: 2.4
Name: astro-drpy
Version: 0.1.11
Summary: A data reduction toolkit for astronomical photometry and spectroscopy.
Author-email: Ruining ZHAO <ruiningzhao@mail.bnu.edu.cn>
Project-URL: Homepage, https://github.com/RuiningZHAO/drpy
Project-URL: Tracker, https://github.com/RuiningZHAO/drpy/issues
Classifier: Programming Language :: Python :: 3
Classifier: License :: OSI Approved :: GNU General Public License v3 (GPLv3)
Classifier: Operating System :: OS Independent
Requires-Python: >=3.7.3
License-File: LICENSE
Requires-Dist: astropy>=4.3
Requires-Dist: numpy>=1.20.1
Requires-Dist: scipy>=1.7.2
Requires-Dist: matplotlib>=3.6.3
Requires-Dist: ccdproc>=2.2.0
Requires-Dist: specutils>=1.7.0
Requires-Dist: photutils>=1.3.0
Dynamic: license-file
